lab03/registerfile.vhd
library IEEE;
use IEEE.std_logic_1164.all;
use IEEE.std_logic_unsigned.all;
use WORK.constants.all;

entity registerfile is
 generic(nbit_data : integer :=  NumBit_data;
	      nbit_addr : integer := NumBit_address);
 port ( CLK: 		IN std_logic;
        RESET: 	IN std_logic;
        ENABLE: 	IN std_logic;
        RD1: 		IN std_logic;
        RD2: 		IN std_logic;
        WR: 		IN std_logic;
        ADD_WR: 	IN PHYSICAL_ADDR;
        ADD_RD1: 	IN PHYSICAL_ADDR;
        ADD_RD2: 	IN PHYSICAL_ADDR;
        DATAIN: 	IN std_logic_vector(nbit_data-1 downto 0);
        OUT1: 		OUT std_logic_vector(nbit_data-1 downto 0);
        OUT2: 		OUT std_logic_vector(nbit_data-1 downto 0));
end registerfile;

architecture A of registerfile is

signal REGISTERS : VIR_REG_ARRAY;

	
begin 
  process (CLK)
    variable TMP_REGISTERS : VIR_REG_ARRAY;

  begin

    if rising_edge(CLK) then

      TMP_REGISTERS := REGISTERS;

      if RESET = '1' then

        for i in PHYSICAL_ADDR loop
          TMP_REGISTERS(i) := (others => '0');
        end loop;

        REGISTERS <= TMP_REGISTERS;
        OUT1 <= (others => '0');
        OUT2 <= (others => '0');

      elsif ENABLE = '1' then

        if WR = '1' then
          TMP_REGISTERS(ADD_WR) := DATAIN;
        end if;

        if RD1 = '1' then
          OUT1 <= TMP_REGISTERS(ADD_RD1);
        end if;

        if RD2 = '1' then
          OUT2 <= TMP_REGISTERS(ADD_RD2);
        end if;

        REGISTERS <= TMP_REGISTERS;
      end if;

    end if;
  end process;
      
  

end A;

lab03/decoder.vhd
library IEEE;
use IEEE.std_logic_1164.all; --  libreria IEEE con definizione tipi standard logic
use IEEE.numeric_std.all;
use WORK.constants.all; -- libreria WORK user-defined

entity DECODER is
  generic ( M: integer := M_const;
	        N: integer := N_const;
            F: integer := F_const;
            nbit_data : integer :=  (3*N+M)/NumBit_address;
            nbit_addr : integer := NumBit_address);
	Port (  CLK: 		IN std_logic;
            RESET: 	    IN std_logic;
            ENABLE: 	IN std_logic;
            RD1: 		IN std_logic;
            RD2: 		IN std_logic;
            WR: 		IN std_logic;
            ADD_WR: 	IN PHYSICAL_ADDR;
            ADD_RD1: 	IN PHYSICAL_ADDR;
            ADD_RD2: 	IN PHYSICAL_ADDR;
            DATAIN: 	IN std_logic_vector(nbit_data-1 downto 0);
            OUT1: 		OUT std_logic_vector(nbit_data-1 downto 0);
            OUT2: 		OUT std_logic_vector(nbit_data-1 downto 0);	
            --decoder
            CALL:	        In	std_logic;          --call flag	
			RET:	        In	std_logic;          --return flag
            SPILL:	        Out	std_logic;	        --SPILL flag
			FILL:	        Out	std_logic;          --FILL flag
            ADD_to_STACK:   Out PHYSICAL_ADDR);     --address for the stack (for the FILL and SPILL operations)
end DECODER;



architecture MIXED of DECODER is

    --LOCAL COUNTERS
    signal CWP, SWP : integer range 0 to F-1;       
    signal used_windows : integer range 0 to F;     --counter for the used windows
    signal stack_counter : integer range 0 to 2*N;  --counter for counting the registers that is necessary to send to the stack 
    
    --LOCAL ADDRESSES
    signal local_ADD_WR : PHYSICAL_ADDR;
    signal local_ADD_RD1 : PHYSICAL_ADDR;
    signal local_ADD_RD2 : PHYSICAL_ADDR;
    signal local_ADDR_Stack : PHYSICAL_ADDR; 
    
    --LOCAL FLAGS
    signal CANSAVE, CANRESTORE : std_logic;

    component registerfile
		generic(nbit_data : integer :=  NumBit_data;
	      nbit_addr : integer := NumBit_address);
        port ( CLK: 		IN std_logic;
                RESET: 	    IN std_logic;
                ENABLE: 	IN std_logic;
                RD1: 		IN std_logic;
                RD2: 		IN std_logic;
                WR: 		IN std_logic;
                ADD_WR: 	IN PHYSICAL_ADDR;
                ADD_RD1: 	IN PHYSICAL_ADDR;
                ADD_RD2: 	IN PHYSICAL_ADDR;
                DATAIN: 	IN std_logic_vector(nbit_data-1 downto 0);
                OUT1: 		OUT std_logic_vector(nbit_data-1 downto 0);
                OUT2: 		OUT std_logic_vector(nbit_data-1 downto 0));
	end component;

begin
    --Translating from the Virtual address (sended) in the real(physical) address for the registers file--
    local_ADD_WR <= ((F * 2 * N) + N + ADD_WR) when (ADD_WR < M)    --Global registers (we used F instead of CWP because they are always at the end of the RF)
                    else ((CWP * 2 * N) + (ADD_WR - M));            --IN/LOCAL/OUT registers (these depend on the value of CWP, the current window)
                    
    local_ADD_RD1 <= ((F * 2 * N) + N + ADD_RD1) when (ADD_RD1 < M) 
                    else ((CWP * 2 * N) + (ADD_RD1 - M));
                    
    local_ADD_RD2 <= ((F * 2 * N) + N + ADD_RD2) when (ADD_RD2 < M) 
                    else ((CWP * 2 * N) + (ADD_RD2 - M));
    -----------

    RF_inst: registerfile
     generic map(
        nbit_data => nbit_data,
        nbit_addr => nbit_addr
    )
     port map(
        CLK     => CLK,         
        RESET   => RESET,
        ENABLE  => ENABLE,
        RD1     => RD1,             --reading1 enable
        RD2     => RD2,             --reading2 enable
        WR      => WR,              --writing enable
        ADD_WR  => local_ADD_WR,    --writing address
        ADD_RD1 => local_ADD_RD1,   --reading1 address
        ADD_RD2 => local_ADD_RD2,   --reading2 address
        DATAIN  => DATAIN,          --writing input
        OUT1    => OUT1,            --reading1 output
        OUT2    => OUT2             --reading2 output
    );

--It's necessary to use a process synchronised with the clock (sensitivity list)
POINTER_UPDATE: process(CLK)
begin
    --The process is evaluated on any change to CLK.
    --This condition restricts actions strictly to the rising edge.
    if rising_edge(CLK) then
        
        -- Reset (all the counters and flags are reset to zero)
        if Reset = '1' then
            CWP <= 0;
            SWP <= 0;
            stack_counter <= 0;
            used_windows <= 1;
            SPILL <= '0';
            FILL <= '0';
            
        --Enable
        elsif Enable = '1' then
            
            --Handle CALL instruction
            if CALL = '1' then
                --At the beginning is necessary to check if there are windows available through CANSAVE

                --Handle SPILL instruction
                if CANSAVE = '0' then
                    --Any windows is available to save(call) operation
                    SPILL <= '1';   --tell the stack that is necessary to SPILL a window to the stack to empty it
                    
                    --This condition is necessary to tell to the RF to wait until all the registers (in the corresponding window) are sended to the stack
                    if stack_counter<2*N then
                        local_ADDR_Stack <= (SWP * 2 * N) + stack_counter; --by 2N instead of 3N because we want only the IN and LOCAL regs because the OUT is the IN of the next window
                        stack_counter <= stack_counter +1;

                    else 
                        --after the regs are sended to the stack a windows become free
                        used_windows <= used_windows - 1;
                        
                        --and the SWP is incremented by one
                        --this is the circular way to execute SWP++
                        if SWP = (F - 1) then
                            SWP <= 0;
                        else
                            SWP <= SWP + 1;
                        end if;
                        SPILL <= '0';       --SPILL is resetted because the operation is finished
                        stack_counter <= 0;

                    end if;

                else --Handle CALL (without SPILL) instruction
                    --the SWP is incremented by one
                    --this is the circular way to execute SWP++
                    if CWP = (F - 1) then
                        CWP <= 0;
                    else
                        CWP <= CWP + 1;
                    end if;

                    used_windows <= used_windows + 1;   --in this case a new window is used(occupied)

                end if;
                
            --Handle RETURN instruction
            elsif RET = '1' then
                
                --Handle FILL instruction
                if CANRESTORE = '0' then
                    --Any windows is available to restore operation
                    FILL <= '1';    --tell the stack that is necessary to FILL a window from the stack to restore it
                    
                    --This condition is necessary to tell to the RF to wait until all the registers (in the corresponding window) are received from the stack
                    if stack_counter<2*N then

                        --in this case is necessary to go back so we need to check if the SWP is zero ro not
                        if SWP = 0 then
                            local_ADDR_Stack <= ((F-1) * 2 *N) + stack_counter;
                        else
                            local_ADDR_Stack <= ((SWP-1) * 2 * N) + stack_counter;
                        end if;

                        stack_counter <= stack_counter +1;
                    else 
                        used_windows <= used_windows + 1;     

                        if SWP = 0 then
                            SWP <= F-1;
                        else
                            SWP <= SWP - 1;
                        end if;
                        FILL <= '0';
                        stack_counter <= 0;
                    end if;
                
                else --Handle RET (without FILL) instruction

                    if CWP = 0 then
                        CWP <= (F - 1);
                    else
                        CWP <= CWP - 1;
                    end if;

                    used_windows <= used_windows - 1;
                end if;
            end if;

        end if;

    end if;
end process;

--Mapping of the signal CANSAVE and CANRESTORE 
CANSAVE <= '1' when (used_windows < F) else '0';    --if there are windows empty -> CANSAVE=1 else CANSAVE=0
CANRESTORE <= '1' when (used_windows > 1) else '0'; --if there are windows available for restoring -> CANRESTORE=1 else CANRESTORE=0

ADD_to_STACK <= local_ADDR_Stack;   --local_ADDR_Stack is mapped to ADD_to_STACK, to connect the cables

end MIXED;

lab03/tb_decoder.vhd
library IEEE;
use IEEE.std_logic_1164.all; --  libreria IEEE con definizione tipi standard logic
use IEEE.numeric_std.all;
use WORK.constants.all; -- libreria WORK user-defined

entity tb_decoder is
end tb_decoder;

architecture tb of tb_decoder is

    component DECODER
        generic ( 
            M: integer := M_const;
            N: integer := N_const;
            F: integer := F_const;
            nbit_data : integer := NumBit_data;
            nbit_addr : integer := NumBit_address
        );
        Port (  
            CLK:            IN std_logic;
            RESET:          IN std_logic;
            ENABLE:         IN std_logic;
            RD1:            IN std_logic;
            RD2:            IN std_logic;
            WR:             IN std_logic;
            ADD_WR:         IN PHYSICAL_ADDR;
            ADD_RD1:        IN PHYSICAL_ADDR;
            ADD_RD2:        IN PHYSICAL_ADDR;
            DATAIN:         IN std_logic_vector(nbit_data-1 downto 0);
            OUT1:           OUT std_logic_vector(nbit_data-1 downto 0);
            OUT2:           OUT std_logic_vector(nbit_data-1 downto 0);	
            CALL:           IN std_logic;	
            RET:            IN std_logic;
            SPILL:          OUT std_logic;	
            FILL:           OUT std_logic;
            ADD_to_STACK:   OUT PHYSICAL_ADDR
        );
    end component;

    constant CLK_PERIOD : time := 10 ns;

    signal CLK_tb          : std_logic := '0';
    signal RESET_tb        : std_logic := '0';
    signal ENABLE_tb       : std_logic := '0';
    signal RD1_tb          : std_logic := '0';
    signal RD2_tb          : std_logic := '0';
    signal WR_tb           : std_logic := '0';
    
    -- Address inputs (using the custom PHYSICAL_ADDR subtype)
    signal ADD_WR_tb       : PHYSICAL_ADDR := 0;
    signal ADD_RD1_tb      : PHYSICAL_ADDR := 0;
    signal ADD_RD2_tb      : PHYSICAL_ADDR := 0;
    
    -- Data buses
    signal DATAIN_tb       : std_logic_vector(NumBit_data-1 downto 0) := (others => '0');
    signal OUT1_tb         : std_logic_vector(NumBit_data-1 downto 0);
    signal OUT2_tb         : std_logic_vector(NumBit_data-1 downto 0);
    
    -- Control and Status Signals
    signal CALL_tb         : std_logic := '0';
    signal RET_tb          : std_logic := '0';
    signal SPILL_tb        : std_logic;
    signal FILL_tb         : std_logic;
    signal ADD_to_STACK_tb : PHYSICAL_ADDR;

begin

    --Unit under test
    uut: DECODER 
        port map (
            CLK          => CLK_tb,
            RESET        => RESET_tb,
            ENABLE       => ENABLE_tb,
            RD1          => RD1_tb,
            RD2          => RD2_tb,
            WR           => WR_tb,
            ADD_WR       => ADD_WR_tb,
            ADD_RD1      => ADD_RD1_tb,
            ADD_RD2      => ADD_RD2_tb,
            DATAIN       => DATAIN_tb,
            OUT1         => OUT1_tb,
            OUT2         => OUT2_tb,
            CALL         => CALL_tb,
            RET          => RET_tb,
            SPILL        => SPILL_tb,
            FILL         => FILL_tb,
            ADD_to_STACK => ADD_to_STACK_tb
        );

    -- Clock Generation Process
    clk_process : process
    begin
        CLK_tb <= '0';
        wait for CLK_PERIOD/2;
        CLK_tb <= '1';
        wait for CLK_PERIOD/2;
    end process;

    -- Main Simulation Process
    sim_process: process
    begin
        ADD_WR_tb  <= 5;  -- Global register test
        ADD_RD1_tb <= 80; -- Window register test
        ADD_RD2_tb <= 85; -- Window register test


        -- 1. INITIALIZATION & RESET
        RESET_tb <= '1';
        wait for CLK_PERIOD * 2;
        RESET_tb <= '0';
        ENABLE_tb <= '1';
        wait for CLK_PERIOD;

        -- 2. CALLs
        CALL_tb <= '1';
        wait for CLK_PERIOD;
        CALL_tb <= '0';
        wait for CLK_PERIOD * 2; -- wait

        CALL_tb <= '1';
        wait for CLK_PERIOD;
        CALL_tb <= '0';
        wait for CLK_PERIOD * 2;

        -- 3. TRIGGERING A SPILL
        CALL_tb <= '1';
        wait for CLK_PERIOD; 
        
        -- The CPU must hold the CALL instruction while SPILL is active.
        -- This loop waits for the stack_counter to reach 2*N.
        while SPILL_tb = '1' loop
            wait for CLK_PERIOD;
        end loop;
        
        CALL_tb <= '0'; -- Instruction completes
        wait for CLK_PERIOD * 3;


        -- 4. RETs
        RET_tb <= '1';
        wait for CLK_PERIOD;
        RET_tb <= '0';
        wait for CLK_PERIOD * 2;


        -- 5. TRIGGERING A FILL
        RET_tb <= '1';
        wait for CLK_PERIOD;
        
        -- The CPU must hold the RET instruction while FILL is active.
        -- This loop waits for the stack_counter to reach 2*N.
        while FILL_tb = '1' loop
            wait for CLK_PERIOD;
        end loop;
        
        RET_tb <= '0'; -- Instruction completes
        wait for CLK_PERIOD * 3;

        wait;
    end process;

end tb;

lab03/output.vcd
$date
  Wed Apr 22 17:19:28 2026
$end
$version
  GHDL v0
$end
$timescale
  1 fs
$end
$scope module standard $end
$upscope $end
$scope module textio $end
$upscope $end
$scope module std_logic_1164 $end
$upscope $end
$scope module numeric_std $end
$upscope $end
$scope module constants $end
$upscope $end
$scope module std_logic_arith $end
$upscope $end
$scope module std_logic_unsigned $end
$upscope $end
$scope module tb_decoder $end
$var reg 1 ! clk_tb $end
$var reg 1 " reset_tb $end
$var reg 1 # enable_tb $end
$var reg 1 $ rd1_tb $end
$var reg 1 % rd2_tb $end
$var reg 1 & wr_tb $end
$var integer 32 ' add_wr_tb $end
$var integer 32 ( add_rd1_tb $end
$var integer 32 ) add_rd2_tb $end
$var reg 64 * datain_tb[63:0] $end
$var reg 64 + out1_tb[63:0] $end
$var reg 64 , out2_tb[63:0] $end
$var reg 1 - call_tb $end
$var reg 1 . ret_tb $end
$var reg 1 / spill_tb $end
$var reg 1 0 fill_tb $end
$var integer 32 1 add_to_stack_tb $end
$scope module uut $end
$var reg 1 2 clk $end
$var reg 1 3 reset $end
$var reg 1 4 enable $end
$var reg 1 5 rd1 $end
$var reg 1 6 rd2 $end
$var reg 1 7 wr $end
$var integer 32 8 add_wr $end
$var integer 32 9 add_rd1 $end
$var integer 32 : add_rd2 $end
$var reg 64 ; datain[63:0] $end
$var reg 64 < out1[63:0] $end
$var reg 64 = out2[63:0] $end
$var reg 1 > call $end
$var reg 1 ? ret $end
$var reg 1 @ spill $end
$var reg 1 A fill $end
$var integer 32 B add_to_stack $end
$var integer 32 C cwp $end
$var integer 32 D swp $end
$var integer 32 E used_windows $end
$var integer 32 F stack_counter $end
$var integer 32 G local_add_wr $end
$var integer 32 H local_add_rd1 $end
$var integer 32 I local_add_rd2 $end
$var integer 32 J local_addr_stack $end
$var reg 1 K cansave $end
$var reg 1 L canrestore $end
$scope module rf_inst $end
$var reg 1 M clk $end
$var reg 1 N reset $end
$var reg 1 O enable $end
$var reg 1 P rd1 $end
$var reg 1 Q rd2 $end
$var reg 1 R wr $end
$var integer 32 S add_wr $end
$var integer 32 T add_rd1 $end
$var integer 32 U add_rd2 $end
$var reg 64 V datain[63:0] $end
$var reg 64 W out1[63:0] $end
$var reg 64 X out2[63:0] $end
$comment registers is not handled $end
$upscope $end
$upscope $end
$upscope $end
$enddefinitions $end
#0
0!
1"
0#
0$
0%
0&
b101 '
b1010000 (
b1010101 )
b0000000000000000000000000000000000000000000000000000000000000000 *
bUUUUUUUUUUUUUUUUUUUUUUUUUUUUUUUUUUUUUUUUUUUUUUUUUUUUUUUUUUUUUUUU +
bUUUUUUUUUUUUUUUUUUUUUUUUUUUUUUUUUUUUUUUUUUUUUUUUUUUUUUUUUUUUUUUU ,
0-
0.
U/
U0
b0 1
02
13
04
05
06
07
b101 8
b1010000 9
b1010101 :
b0000000000000000000000000000000000000000000000000000000000000000 ;
bUUUUUUUUUUUUUUUUUUUUUUUUUUUUUUUUUUUUUUUUUUUUUUUUUUUUUUUUUUUUUUUU <
bUUUUUUUUUUUUUUUUUUUUUUUUUUUUUUUUUUUUUUUUUUUUUUUUUUUUUUUUUUUUUUUU =
0>
0?
U@
UA
b0 B
b0 C
b0 D
b0 E
b0 F
b10011000 G
b111 H
b1100 I
b0 J
1K
0L
0M
1N
0O
0P
0Q
0R
b10011000 S
b111 T
b1100 U
b0000000000000000000000000000000000000000000000000000000000000000 V
bUUUUUUUUUUUUUUUUUUUUUUUUUUUUUUUUUUUUUUUUUUUUUUUUUUUUUUUUUUUUUUUU W
bUUUUUUUUUUUUUUUUUUUUUUUUUUUUUUUUUUUUUUUUUUUUUUUUUUUUUUUUUUUUUUUU X
#5000000
1!
b0000000000000000000000000000000000000000000000000000000000000000 +
b0000000000000000000000000000000000000000000000000000000000000000 ,
0/
00
12
b0000000000000000000000000000000000000000000000000000000000000000 <
b0000000000000000000000000000000000000000000000000000000000000000 =
0@
0A
b1 E
1M
b0000000000000000000000000000000000000000000000000000000000000000 W
b0000000000000000000000000000000000000000000000000000000000000000 X
#10000000
0!
02
0M
#15000000
1!
12
1M
#20000000
0!
0"
1#
02
03
14
0M
0N
1O
#25000000
1!
12
1M
#30000000
0!
1-
02
1>
0M
#35000000
1!
12
b1 C
b10 E
b110001 H
b110110 I
1L
1M
b110001 T
b110110 U
#40000000
0!
0-
02
0>
0M
#45000000
1!
12
1M
#50000000
0!
02
0M
#55000000
1!
12
1M
#60000000
0!
1-
02
1>
0M
#65000000
1!
12
b10 C
b11 E
b1011011 H
b1100000 I
0K
1M
b1011011 T
b1100000 U
#70000000
0!
0-
02
0>
0M
#75000000
1!
12
1M
#80000000
0!
02
0M
#85000000
1!
12
1M
#90000000
0!
1-
02
1>
0M
#95000000
1!
1/
12
1@
b1 F
1M
#100000000
0!
02
0M
#105000000
1!
b1 1
12
b1 B
b10 F
b1 J
1M
#110000000
0!
02
0M
#115000000
1!
b10 1
12
b10 B
b11 F
b10 J
1M
#120000000
0!
02
0M
#125000000
1!
b11 1
12
b11 B
b100 F
b11 J
1M
#130000000
0!
02
0M
#135000000
1!
b100 1
12
b100 B
b101 F
b100 J
1M
#140000000
0!
02
0M
#145000000
1!
b101 1
12
b101 B
b110 F
b101 J
1M
#150000000
0!
02
0M
#155000000
1!
b110 1
12
b110 B
b111 F
b110 J
1M
#160000000
0!
02
0M
#165000000
1!
b111 1
12
b111 B
b1000 F
b111 J
1M
#170000000
0!
02
0M
#175000000
1!
b1000 1
12
b1000 B
b1001 F
b1000 J
1M
#180000000
0!
02
0M
#185000000
1!
b1001 1
12
b1001 B
b1010 F
b1001 J
1M
#190000000
0!
02
0M
#195000000
1!
b1010 1
12
b1010 B
b1011 F
b1010 J
1M
#200000000
0!
02
0M
#205000000
1!
b1011 1
12
b1011 B
b1100 F
b1011 J
1M
#210000000
0!
02
0M
#215000000
1!
b1100 1
12
b1100 B
b1101 F
b1100 J
1M
#220000000
0!
02
0M
#225000000
1!
b1101 1
12
b1101 B
b1110 F
b1101 J
1M
#230000000
0!
02
0M
#235000000
1!
b1110 1
12
b1110 B
b1111 F
b1110 J
1M
#240000000
0!
02
0M
#245000000
1!
b1111 1
12
b1111 B
b10000 F
b1111 J
1M
#250000000
0!
02
0M
#255000000
1!
b10000 1
12
b10000 B
b10001 F
b10000 J
1M
#260000000
0!
02
0M
#265000000
1!
b10001 1
12
b10001 B
b10010 F
b10001 J
1M
#270000000
0!
02
0M
#275000000
1!
b10010 1
12
b10010 B
b10011 F
b10010 J
1M
#280000000
0!
02
0M
#285000000
1!
b10011 1
12
b10011 B
b10100 F
b10011 J
1M
#290000000
0!
02
0M
#295000000
1!
b10100 1
12
b10100 B
b10101 F
b10100 J
1M
#300000000
0!
02
0M
#305000000
1!
b10101 1
12
b10101 B
b10110 F
b10101 J
1M
#310000000
0!
02
0M
#315000000
1!
b10110 1
12
b10110 B
b10111 F
b10110 J
1M
#320000000
0!
02
0M
#325000000
1!
b10111 1
12
b10111 B
b11000 F
b10111 J
1M
#330000000
0!
02
0M
#335000000
1!
b11000 1
12
b11000 B
b11001 F
b11000 J
1M
#340000000
0!
02
0M
#345000000
1!
b11001 1
12
b11001 B
b11010 F
b11001 J
1M
#350000000
0!
02
0M
#355000000
1!
b11010 1
12
b11010 B
b11011 F
b11010 J
1M
#360000000
0!
02
0M
#365000000
1!
b11011 1
12
b11011 B
b11100 F
b11011 J
1M
#370000000
0!
02
0M
#375000000
1!
b11100 1
12
b11100 B
b11101 F
b11100 J
1M
#380000000
0!
02
0M
#385000000
1!
b11101 1
12
b11101 B
b11110 F
b11101 J
1M
#390000000
0!
02
0M
#395000000
1!
b11110 1
12
b11110 B
b11111 F
b11110 J
1M
#400000000
0!
02
0M
#405000000
1!
b11111 1
12
b11111 B
b100000 F
b11111 J
1M
#410000000
0!
02
0M
#415000000
1!
b100000 1
12
b100000 B
b100001 F
b100000 J
1M
#420000000
0!
02
0M
#425000000
1!
b100001 1
12
b100001 B
b100010 F
b100001 J
1M
#430000000
0!
02
0M
#435000000
1!
b100010 1
12
b100010 B
b100011 F
b100010 J
1M
#440000000
0!
02
0M
#445000000
1!
b100011 1
12
b100011 B
b100100 F
b100011 J
1M
#450000000
0!
02
0M
#455000000
1!
b100100 1
12
b100100 B
b100101 F
b100100 J
1M
#460000000
0!
02
0M
#465000000
1!
b100101 1
12
b100101 B
b100110 F
b100101 J
1M
#470000000
0!
02
0M
#475000000
1!
b100110 1
12
b100110 B
b100111 F
b100110 J
1M
#480000000
0!
02
0M
#485000000
1!
b100111 1
12
b100111 B
b101000 F
b100111 J
1M
#490000000
0!
02
0M
#495000000
1!
b101000 1
12
b101000 B
b101001 F
b101000 J
1M
#500000000
0!
02
0M
#505000000
1!
b101001 1
12
b101001 B
b101010 F
b101001 J
1M
#510000000
0!
02
0M
#515000000
1!
0/
12
0@
b1 D
b10 E
b0 F
1K
1M
#520000000
0!
0-
02
0>
0M
#525000000
1!
12
1M
#530000000
0!
02
0M
#535000000
1!
12
1M
#540000000
0!
02
0M
#545000000
1!
12
1M
#550000000
0!
1.
02
1?
0M
#555000000
1!
12
b1 C
b1 E
b110001 H
b110110 I
0L
1M
b110001 T
b110110 U
#560000000
0!
0.
02
0?
0M
#565000000
1!
12
1M
#570000000
0!
02
0M
#575000000
1!
12
1M
#580000000
0!
1.
02
1?
0M
#585000000
1!
10
b0 1
12
1A
b0 B
b1 F
b0 J
1M
#590000000
0!
02
0M
#595000000
1!
b1 1
12
b1 B
b10 F
b1 J
1M
#600000000
0!
02
0M
#605000000
1!
b10 1
12
b10 B
b11 F
b10 J
1M
#610000000
0!
02
0M
#615000000
1!
b11 1
12
b11 B
b100 F
b11 J
1M
#620000000
0!
02
0M
#625000000
1!
b100 1
12
b100 B
b101 F
b100 J
1M
#630000000
0!
02
0M
#635000000
1!
b101 1
12
b101 B
b110 F
b101 J
1M
#640000000
0!
02
0M
#645000000
1!
b110 1
12
b110 B
b111 F
b110 J
1M
#650000000
0!
02
0M
#655000000
1!
b111 1
12
b111 B
b1000 F
b111 J
1M
#660000000
0!
02
0M
#665000000
1!
b1000 1
12
b1000 B
b1001 F
b1000 J
1M
#670000000
0!
02
0M
#675000000
1!
b1001 1
12
b1001 B
b1010 F
b1001 J
1M
#680000000
0!
02
0M
#685000000
1!
b1010 1
12
b1010 B
b1011 F
b1010 J
1M
#690000000
0!
02
0M
#695000000
1!
b1011 1
12
b1011 B
b1100 F
b1011 J
1M
#700000000
0!
02
0M
#705000000
1!
b1100 1
12
b1100 B
b1101 F
b1100 J
1M
#710000000
0!
02
0M
#715000000
1!
b1101 1
12
b1101 B
b1110 F
b1101 J
1M
#720000000
0!
02
0M
#725000000
1!
b1110 1
12
b1110 B
b1111 F
b1110 J
1M
#730000000
0!
02
0M
#735000000
1!
b1111 1
12
b1111 B
b10000 F
b1111 J
1M
#740000000
0!
02
0M
#745000000
1!
b10000 1
12
b10000 B
b10001 F
b10000 J
1M
#750000000
0!
02
0M
#755000000
1!
b10001 1
12
b10001 B
b10010 F
b10001 J
1M
#760000000
0!
02
0M
#765000000
1!
b10010 1
12
b10010 B
b10011 F
b10010 J
1M
#770000000
0!
02
0M
#775000000
1!
b10011 1
12
b10011 B
b10100 F
b10011 J
1M
#780000000
0!
02
0M
#785000000
1!
b10100 1
12
b10100 B
b10101 F
b10100 J
1M
#790000000
0!
02
0M
#795000000
1!
b10101 1
12
b10101 B
b10110 F
b10101 J
1M
#800000000
0!
02
0M
#805000000
1!
b10110 1
12
b10110 B
b10111 F
b10110 J
1M
#810000000
0!
02
0M
#815000000
1!
b10111 1
12
b10111 B
b11000 F
b10111 J
1M
#820000000
0!
02
0M
#825000000
1!
b11000 1
12
b11000 B
b11001 F
b11000 J
1M
#830000000
0!
02
0M
#835000000
1!
b11001 1
12
b11001 B
b11010 F
b11001 J
1M
#840000000
0!
02
0M
#845000000
1!
b11010 1
12
b11010 B
b11011 F
b11010 J
1M
#850000000
0!
02
0M
#855000000
1!
b11011 1
12
b11011 B
b11100 F
b11011 J
1M
#860000000
0!
02
0M
#865000000
1!
b11100 1
12
b11100 B
b11101 F
b11100 J
1M
#870000000
0!
02
0M
#875000000
1!
b11101 1
12
b11101 B
b11110 F
b11101 J
1M
#880000000
0!
02
0M
#885000000
1!
b11110 1
12
b11110 B
b11111 F
b11110 J
1M
#890000000
0!
02
0M
#895000000
1!
b11111 1
12
b11111 B
b100000 F
b11111 J
1M
#900000000
0!
02
0M
#905000000
1!
b100000 1
12
b100000 B
b100001 F
b100000 J
1M
#910000000
0!
02
0M
#915000000
1!
b100001 1
12
b100001 B
b100010 F
b100001 J
1M
#920000000
0!
02
0M
#925000000
1!
b100010 1
12
b100010 B
b100011 F
b100010 J
1M
#930000000
0!
02
0M
#935000000
1!
b100011 1
12
b100011 B
b100100 F
b100011 J
1M
#940000000
0!
02
0M
#945000000
1!
b100100 1
12
b100100 B
b100101 F
b100100 J
1M
#950000000
0!
02
0M
#955000000
1!
b100101 1
12
b100101 B
b100110 F
b100101 J
1M
#960000000
0!
02
0M
#965000000
1!
b100110 1
12
b100110 B
b100111 F
b100110 J
1M
#970000000
0!
02
0M
#975000000
1!
b100111 1
12
b100111 B
b101000 F
b100111 J
1M
#980000000
0!
02
0M
#985000000
1!
b101000 1
12
b101000 B
b101001 F
b101000 J
1M
#990000000
0!
02
0M
#995000000
1!
b101001 1
12
b101001 B
b101010 F
b101001 J
1M
#1000000000
0!
02
0M
#1005000000
1!
00
12
0A
b0 D
b10 E
b0 F
1L
1M
#1010000000
0!
0.
02
0?
0M
